disl.py
tests/demo.py
tests/disl_test.py
disl-0.0.4.dist-info/LICENSE
disl-0.0.4.dist-info/METADATA
disl-0.0.4.dist-info/WHEEL
disl-0.0.4.dist-info/top_level.txt
disl-0.0.4.dist-info/RECORD
