Metadata-Version: 2.1
Name: disl
Version: 0.0.4
Summary: A super lightweight (only 35 lines) dependency injection (ioc) support for Python.
Home-page: https://github.com/freemant2000/dilite
Author: Kent Tong
Author-email: kent.tong.mo@gmail.com
Project-URL: Bug Tracker, https://github.com/freemant2000/dilite/issues
Classifier: Programming Language :: Python :: 3
Classifier: License :: OSI Approved :: Apache Software License
Classifier: Operating System :: OS Independent
Requires-Python: >=3.6
License-File: LICENSE
